shadowsocks/common.py
shadowsocks/asyncdns.py
shadowsocks/__init__.py
shadowsocks/udprelay.py
shadowsocks/encrypt.py
shadowsocks/local.py
shadowsocks/lru_cache.py
shadowsocks/tcprelay.py
shadowsocks/daemon.py
shadowsocks/manager.py
shadowsocks/shell.py
shadowsocks/server.py
shadowsocks/eventloop.py
shadowsocks/crypto/__init__.py
shadowsocks/crypto/rc4_md5.py
shadowsocks/crypto/table.py
shadowsocks/crypto/openssl.py
shadowsocks/crypto/util.py
shadowsocks/crypto/sodium.py
shadowsocks_c-2.8.2.dist-info/entry_points.txt
shadowsocks_c-2.8.2.dist-info/metadata.json
shadowsocks_c-2.8.2.dist-info/WHEEL
shadowsocks_c-2.8.2.dist-info/METADATA
shadowsocks_c-2.8.2.dist-info/DESCRIPTION.rst
shadowsocks_c-2.8.2.dist-info/RECORD
shadowsocks_c-2.8.2.dist-info/top_level.txt
