Metadata-Version: 2.0
Name: shadowsocks-c
Version: 2.8.2
Summary: shadowsocks clone with linux pluggable congestion control support
Home-page: https://github.com/zxjcarrot/shadowsocks
Author: zxjcarrot
Author-email: zxjcarrot@gmail.com
License: http://www.apache.org/licenses/LICENSE-2.0
Platform: UNKNOWN
Classifier: License :: OSI Approved :: Apache Software License
Classifier: Programming Language :: Python :: 2
Classifier: Programming Language :: Python :: 2.6
Classifier: Programming Language :: Python :: 2.7
Classifier: Programming Language :: Python :: 3
Classifier: Programming Language :: Python :: 3.3
Classifier: Programming Language :: Python :: 3.4
Classifier: Programming Language :: Python :: Implementation :: CPython
Classifier: Programming Language :: Python :: Implementation :: PyPy
Classifier: Topic :: Internet :: Proxy Servers
